{
  "girls_only_deep_pack": [
    {"id": 1, "text": "pleuré en regardant une publicité"},
    {"id": 2, "text": "acheté des vêtements pour une occasion spécifique et ne jamais les porter"},
    {"id": 3, "text": "porté des talons toute la journée et souffert"},
    {"id": 4, "text": "eu une crise de garde-robe avant de sortir"},
    {"id": 5, "text": "essayé tous les vêtements de mon placard"},
    {"id": 6, "text": "acheté la même chose en plusieurs couleurs"},
    {"id": 7, "text": "gardé des vêtements qui ne me vont plus"},
    {"id": 8, "text": "caché des achats à quelqu'un"},
    {"id": 9, "text": "menti sur le prix de quelque chose"},
    {"id": 10, "text": "acheté quelque chose en solde dont je n'avais pas besoin"},
    {"id": 11, "text": "regretté une coupe de cheveux immédiatement"},
    {"id": 12, "text": "pleuré chez le coiffeur"},
    {"id": 13, "text": "coupé ma propre frange et regretté"},
    {"id": 14, "text": "décoloré mes cheveux et les avoir abîmés"},
    {"id": 15, "text": "porté une perruque ou des extensions"},
    {"id": 16, "text": "passé plus d'une heure à me coiffer"},
    {"id": 17, "text": "dormi avec les cheveux mouillés"},
    {"id": 18, "text": "utilisé du shampoing sec pendant plusieurs jours"},
    {"id": 19, "text": "coloré mes cheveux à la maison"},
    {"id": 20, "text": "brûlé mes cheveux avec un fer"},
    {"id": 21, "text": "dépensé une fortune en produits capillaires"},
    {"id": 22, "text": "eu une collection de pinces à cheveux"},
    {"id": 23, "text": "perdu des dizaines d'élastiques à cheveux"},
    {"id": 24, "text": "porté un chouchou au poignet"},
    {"id": 25, "text": "fait un chignon désordonné comme coiffure par défaut"},
    {"id": 26, "text": "regardé des tutoriels de coiffure sur YouTube"},
    {"id": 27, "text": "échoué à recréer une coiffure Pinterest"},
    {"id": 28, "text": "passé des heures à me maquiller"},
    {"id": 29, "text": "acheté du maquillage parce qu'un influenceur l'a recommandé"},
    {"id": 30, "text": "possédé plus de 10 rouges à lèvres"},
    {"id": 31, "text": "collectionné des palettes de maquillage"},
    {"id": 32, "text": "jeté du maquillage périmé"},
    {"id": 33, "text": "utilisé du maquillage après sa date d'expiration"},
    {"id": 34, "text": "partagé du maquillage avec des amies"},
    {"id": 35, "text": "maquillé dans la voiture"},
    {"id": 36, "text": "réparé mon maquillage en public"},
    {"id": 37, "text": "porté un sac de maquillage partout"},
    {"id": 38, "text": "fait un maquillage complet sans raison"},
    {"id": 39, "text": "regardé des vidéos de transformation maquillage"},
    {"id": 40, "text": "essayé un look dramatique"},
    {"id": 41, "text": "lutté avec l'eye-liner ailé"},
    {"id": 42, "text": "utilisé du ruban adhésif pour l'eye-liner"},
    {"id": 43, "text": "piqué mon œil avec du mascara"},
    {"id": 44, "text": "éternué après avoir appliqué du mascara"},
    {"id": 45, "text": "mis du mascara sur ma paupière"},
    {"id": 46, "text": "essayé des faux cils magnétiques"},
    {"id": 47, "text": "eu du mal à appliquer des faux cils"},
    {"id": 48, "text": "perdu un faux cil"},
    {"id": 49, "text": "sur-épilé mes sourcils"},
    {"id": 50, "text": "dessiné mes sourcils"},
    {"id": 51, "text": "fait faire un microblading"},
    {"id": 52, "text": "utilisé un crayon à sourcils"},
    {"id": 53, "text": "fait épiler mes sourcils au fil"},
    {"id": 54, "text": "formé mes sourcils moi-même"},
    {"id": 55, "text": "suivi la tendance des sourcils du moment"},
    {"id": 56, "text": "regretté des sourcils fins"},
    {"id": 57, "text": "essayé de faire repousser mes sourcils"},
    {"id": 58, "text": "utilisé de l'huile de ricin pour la croissance"},
    {"id": 59, "text": "pris des vitamines pour les cheveux"},
    {"id": 60, "text": "pris des suppléments de collagène"},
    {"id": 61, "text": "essayé la biotine"},
    {"id": 62, "text": "pris des vitamines quotidiennes"},
    {"id": 63, "text": "bu des smoothies verts"},
    {"id": 64, "text": "essayé des shakes protéinés"},
    {"id": 65, "text": "préparé les repas pour la semaine"},
    {"id": 66, "text": "cuisiné une recette Pinterest"},
    {"id": 67, "text": "essayé une recette virale"},
    {"id": 68, "text": "fait de la pâtisserie de zéro"},
    {"id": 69, "text": "décoré des cupcakes"},
    {"id": 70, "text": "organisé un brunch"},
    {"id": 71, "text": "fait un plateau de charcuterie"},
    {"id": 72, "text": "acheté des articles de cuisine esthétiques"},
    {"id": 73, "text": "organisé mon garde-manger joliment"},
    {"id": 74, "text": "utilisé des contenants transparents"},
    {"id": 75, "text": "étiqueté tout dans ma maison"},
    {"id": 76, "text": "redécoré ma chambre"},
    {"id": 77, "text": "acheté des coussins décoratifs"},
    {"id": 78, "text": "accroché des guirlandes lumineuses"},
    {"id": 79, "text": "créé un mur de galerie"},
    {"id": 80, "text": "acheté des plantes pour mon espace"},
    {"id": 81, "text": "tué une plante"},
    {"id": 82, "text": "nommé mes plantes"},
    {"id": 83, "text": "pris des photos esthétiques de mon espace"},
    {"id": 84, "text": "réarrangé mes meubles plusieurs fois"},
    {"id": 85, "text": "eu une coiffeuse"},
    {"id": 86, "text": "organisé mes bijoux"},
    {"id": 87, "text": "eu une boîte à bijoux"},
    {"id": 88, "text": "porté des boucles d'oreilles statement"},
    {"id": 89, "text": "superposé des colliers"},
    {"id": 90, "text": "empilé des bagues"},
    {"id": 91, "text": "porté une chaîne de cheville"},
    {"id": 92, "text": "fait percer le cartilage"},
    {"id": 93, "text": "fait plusieurs piercings d'oreille"},
    {"id": 94, "text": "fait un piercing au nez"},
    {"id": 95, "text": "fait un piercing au nombril"},
    {"id": 96, "text": "regretté un piercing"},
    {"id": 97, "text": "eu une infection d'un piercing"},
    {"id": 98, "text": "fait un tatouage"},
    {"id": 99, "text": "fait un tatouage assorti avec des amies"},
    {"id": 100, "text": "fait un tatouage significatif"},
    {"id": 101, "text": "fait un tatouage impulsif"},
    {"id": 102, "text": "regretté un tatouage"},
    {"id": 103, "text": "planifié un tatouage pendant des années"},
    {"id": 104, "text": "recherché des tatoueurs en profondeur"},
    {"id": 105, "text": "conçu mon propre tatouage"},
    {"id": 106, "text": "fait un petit tatouage délicat"},
    {"id": 107, "text": "fait tatouer une citation"},
    {"id": 108, "text": "fait un tatouage floral"},
    {"id": 109, "text": "fait un tatouage de papillon"},
    {"id": 110, "text": "fait un tatouage de lune ou étoile"},
    {"id": 111, "text": "fait un tatouage minimaliste"},
    {"id": 112, "text": "montré mon tatouage sur les réseaux sociaux"},
    {"id": 113, "text": "caché un tatouage à mes parents"},
    {"id": 114, "text": "fait un tatouage dans un endroit caché"},
    {"id": 115, "text": "été interrogée sur la signification de mon tatouage"},
    {"id": 116, "text": "eu mes règles au mauvais moment"},
    {"id": 117, "text": "eu des crampes qui ont ruiné ma journée"},
    {"id": 118, "text": "appelé malade à cause de mes règles"},
    {"id": 119, "text": "porté des sous-vêtements menstruels"},
    {"id": 120, "text": "essayé une coupe menstruelle"},
    {"id": 121, "text": "suivi mon cycle"},
    {"id": 122, "text": "eu des sautes d'humeur SPM"},
    {"id": 123, "text": "eu envie de chocolat pendant mes règles"},
    {"id": 124, "text": "pris la pilule"},
    {"id": 125, "text": "fait un test de grossesse par précaution"},
    {"id": 126, "text": "été chez un gynécologue"},
    {"id": 127, "text": "fait un frottis"},
    {"id": 128, "text": "eu une infection urinaire"},
    {"id": 129, "text": "traité une mycose"},
    {"id": 130, "text": "épilé avant un rendez-vous"},
    {"id": 131, "text": "planifié ma tenue autour de mes sous-vêtements"},
    {"id": 132, "text": "possédé des ensembles de lingerie assortis"},
    {"id": 133, "text": "acheté de la lingerie pour que quelqu'un la voie"},
    {"id": 134, "text": "porté un soutien-gorge push-up"},
    {"id": 135, "text": "porté un soutien-gorge sans bretelles"},
    {"id": 136, "text": "ajusté mon soutien-gorge en public"},
    {"id": 137, "text": "porté une robe dos nu avec des sous-vêtements spéciaux"},
    {"id": 138, "text": "utilisé du ruban de mode"},
    {"id": 139, "text": "porté des cache-tétons"},
    {"id": 140, "text": "eu un problème de garde-robe lié à la poitrine"},
    {"id": 141, "text": "me suis plainte des prix des soutiens-gorge"},
    {"id": 142, "text": "été mesurée pour une bonne taille de soutien-gorge"},
    {"id": 143, "text": "découvert que je portais la mauvaise taille"},
    {"id": 144, "text": "retiré immédiatement mon soutien-gorge en rentrant"},
    {"id": 145, "text": "dormi avec un soutien-gorge"},
    {"id": 146, "text": "porté le même soutien-gorge plusieurs jours d'affilée"},
    {"id": 147, "text": "lavé à la main des articles délicats"},
    {"id": 148, "text": "abîmé quelque chose en le lavant mal"},
    {"id": 149, "text": "eu un vêtement nettoyage à sec uniquement"},
    {"id": 150, "text": "repassé une tenue juste avant de la porter"},
    {"id": 151, "text": "fait une manucure à la maison"},
    {"id": 152, "text": "raté mes ongles"},
    {"id": 153, "text": "attendu que mes ongles sèchent"},
    {"id": 154, "text": "abîmé mes ongles juste après les avoir faits"},
    {"id": 155, "text": "eu des ongles en gel"},
    {"id": 156, "text": "eu des ongles en acrylique"},
    {"id": 157, "text": "cassé un ongle et été dévastée"},
    {"id": 158, "text": "dépensé une fortune en ongles"},
    {"id": 159, "text": "collectionné des vernis à ongles"},
    {"id": 160, "text": "essayé du nail art"},
    {"id": 161, "text": "regardé des tutoriels de nail art"},
    {"id": 162, "text": "fait une pédicure à la maison"},
    {"id": 163, "text": "peint mes orteils"},
    {"id": 164, "text": "porté des tongs pour que mes ongles sèchent"},
    {"id": 165, "text": "eu une routine de soins de la peau"},
    {"id": 166, "text": "essayé une routine coréenne en 10 étapes"},
    {"id": 167, "text": "utilisé des masques en tissu"},
    {"id": 168, "text": "essayé des patchs pour les yeux"},
    {"id": 169, "text": "utilisé un rouleau de jade"},
    {"id": 170, "text": "essayé un gua sha"},
    {"id": 171, "text": "fait un masque facial"},
    {"id": 172, "text": "fait un masque DIY"},
    {"id": 173, "text": "eu une routine du matin"},
    {"id": 174, "text": "eu une routine du soir"},
    {"id": 175, "text": "dormi avec un masque de nuit"},
    {"id": 176, "text": "utilisé des crèmes pour les yeux"},
    {"id": 177, "text": "essayé des sérums"},
    {"id": 178, "text": "utilisé de la vitamine C"},
    {"id": 179, "text": "essayé du rétinol"},
    {"id": 180, "text": "utilisé de l'acide hyaluronique"},
    {"id": 181, "text": "dépensé trop en soins de la peau"},
    {"id": 182, "text": "recherché des ingrédients"},
    {"id": 183, "text": "lu des avis de produits"},
    {"id": 184, "text": "rejoint une communauté de soins de la peau"},
    {"id": 185, "text": "partagé ma routine"},
    {"id": 186, "text": "demandé des recommandations"},
    {"id": 187, "text": "essayé des échantillons"},
    {"id": 188, "text": "commandé des produits en ligne"},
    {"id": 189, "text": "attendu impatiemment une livraison"},
    {"id": 190, "text": "déballé des produits de beauté"},
    {"id": 191, "text": "fait un haul beauté"},
    {"id": 192, "text": "regardé des vidéos de haul"},
    {"id": 193, "text": "suivi des influenceurs beauté"},
    {"id": 194, "text": "été influencée par les réseaux sociaux"},
    {"id": 195, "text": "acheté à cause d'une pub"},
    {"id": 196, "text": "regretté un achat impulsif"},
    {"id": 197, "text": "retourné des produits de beauté"},
    {"id": 198, "text": "échangé des produits avec des amies"},
    {"id": 199, "text": "donné des produits que je n'aimais pas"},
    {"id": 200, "text": "gardé des produits que je n'utilise pas"},
    {"id": 201, "text": "organisé mes produits de beauté"},
    {"id": 202, "text": "acheté du rangement pour le maquillage"},
    {"id": 203, "text": "créé un espace beauté"},
    {"id": 204, "text": "rêvé d'un dressing de rêve"},
    {"id": 205, "text": "épinglé des intérieurs sur Pinterest"},
    {"id": 206, "text": "suivi des comptes de décoration"},
    {"id": 207, "text": "voulu redécorer ma maison"},
    {"id": 208, "text": "magasiné pour de la décoration"},
    {"id": 209, "text": "acheté des bougies"},
    {"id": 210, "text": "collectionné des bougies parfumées"},
    {"id": 211, "text": "créé une ambiance avec des bougies"},
    {"id": 212, "text": "pris un bain avec des bougies"},
    {"id": 213, "text": "fait un spa à la maison"},
    {"id": 214, "text": "eu une soirée self-care"},
    {"id": 215, "text": "médité"},
    {"id": 216, "text": "pratiqué le yoga"},
    {"id": 217, "text": "tenu un journal"},
    {"id": 218, "text": "pratiqué la gratitude"},
    {"id": 219, "text": "fait des affirmations"},
    {"id": 220, "text": "travaillé sur moi-même"},
    {"id": 221, "text": "lu des livres de développement personnel"},
    {"id": 222, "text": "écouté des podcasts motivants"},
    {"id": 223, "text": "suivi un cours en ligne"},
    {"id": 224, "text": "appris une nouvelle compétence"},
    {"id": 225, "text": "commencé un nouveau hobby"},
    {"id": 226, "text": "rejoint un club"},
    {"id": 227, "text": "fait du bénévolat"},
    {"id": 228, "text": "aidé une cause"},
    {"id": 229, "text": "fait un don"},
    {"id": 230, "text": "soutenu des petites entreprises"},
    {"id": 231, "text": "acheté local"},
    {"id": 232, "text": "fait du shopping éthique"},
    {"id": 233, "text": "choisi des produits durables"},
    {"id": 234, "text": "réduit ma consommation de plastique"},
    {"id": 235, "text": "recyclé"},
    {"id": 236, "text": "composté"},
    {"id": 237, "text": "fait des efforts pour l'environnement"},
    {"id": 238, "text": "changé mes habitudes"},
    {"id": 239, "text": "essayé d'être plus consciente"},
    {"id": 240, "text": "partagé mes valeurs"},
    {"id": 241, "text": "défendu ce en quoi je crois"},
    {"id": 242, "text": "été activiste"},
    {"id": 243, "text": "assisté à une manifestation"},
    {"id": 244, "text": "signé des pétitions"},
    {"id": 245, "text": "utilisé ma voix"},
    {"id": 246, "text": "soutenu d'autres femmes"},
    {"id": 247, "text": "célébré les succès féminins"},
    {"id": 248, "text": "été un mentor"},
    {"id": 249, "text": "aidé une autre femme"},
    {"id": 250, "text": "partagé mes connaissances"},
    {"id": 251, "text": "encouragé quelqu'un"},
    {"id": 252, "text": "complimenté une inconnue"},
    {"id": 253, "text": "fait une amie dans les toilettes"},
    {"id": 254, "text": "aidé quelqu'un avec une urgence de garde-robe"},
    {"id": 255, "text": "partagé des produits féminins"},
    {"id": 256, "text": "été là pour une amie"},
    {"id": 257, "text": "écouté sans juger"},
    {"id": 258, "text": "gardé un secret"},
    {"id": 259, "text": "été une bonne amie"},
    {"id": 260, "text": "valorisé mes amitiés féminines"},
    {"id": 261, "text": "eu une tribu de filles"},
    {"id": 262, "text": "fait des soirées entre filles"},
    {"id": 263, "text": "eu des traditions entre filles"},
    {"id": 264, "text": "voyagé avec des amies"},
    {"id": 265, "text": "fait un voyage entre filles"},
    {"id": 266, "text": "eu une escapade de fin de semaine"},
    {"id": 267, "text": "partagé une chambre d'hôtel"},
    {"id": 268, "text": "pris des millions de photos"},
    {"id": 269, "text": "été photographe pour des amies"},
    {"id": 270, "text": "posé pour des photos"},
    {"id": 271, "text": "refait des photos plusieurs fois"},
    {"id": 272, "text": "édité des photos"},
    {"id": 273, "text": "utilisé des filtres"},
    {"id": 274, "text": "choisi la meilleure photo"},
    {"id": 275, "text": "demandé l'avis avant de poster"},
    {"id": 276, "text": "supprimé une photo après l'avoir postée"},
    {"id": 277, "text": "regretté une publication"},
    {"id": 278, "text": "sur-analysé un post"},
    {"id": 279, "text": "vérifié les likes constamment"},
    {"id": 280, "text": "comparé mes likes"},
    {"id": 281, "text": "été affectée par les réseaux sociaux"},
    {"id": 282, "text": "fait une pause des réseaux sociaux"},
    {"id": 283, "text": "supprimé une application"},
    {"id": 284, "text": "limité mon temps d'écran"},
    {"id": 285, "text": "réalisé l'impact des réseaux sociaux"},
    {"id": 286, "text": "comparé ma vie aux autres"},
    {"id": 287, "text": "senti FOMO"},
    {"id": 288, "text": "été jalouse des publications de quelqu'un"},
    {"id": 289, "text": "scrollé pendant des heures"},
    {"id": 290, "text": "perdu du temps sur les réseaux sociaux"},
    {"id": 291, "text": "essayé de décrocher"},
    {"id": 292, "text": "travaillé sur mon bien-être mental"},
    {"id": 293, "text": "priorisé ma santé mentale"},
    {"id": 294, "text": "cherché de l'aide"},
    {"id": 295, "text": "parlé à un thérapeute"},
    {"id": 296, "text": "pratiqué le self-care"},
    {"id": 297, "text": "appris à m'aimer"},
    {"id": 298, "text": "grandi en tant que femme"},
    {"id": 299, "text": "embrassé ma féminité"},
    {"id": 300, "text": "été fière d'être une femme"}
  ]
}